{
    "key": "group_psm_mission_statement_page",
    "title": "Board Mission Statement Page",
    "fields": [
        {
            "key": "field_psm_ms_tab_banner",
            "label": "Inner Banner",
            "name": "",
            "type": "tab",
            "placement": "top",
            "endpoint": 0,
            "selected": 1
        },
        {
            "key": "field_psm_inner_banner_kicker_ms",
            "label": "Kicker",
            "name": "inner_banner_kicker",
            "type": "text",
            "instructions": "Small line above the page title.",
            "default_value": "Welcome to Port St Mary Commissioners Board"
        },
        {
            "key": "field_psm_inner_banner_title_ms",
            "label": "Heading",
            "name": "inner_banner_title",
            "type": "text",
            "instructions": "Main page heading (H1).",
            "default_value": "Mission Statement"
        },
        {
            "key": "field_psm_inner_banner_ribbon_ms",
            "label": "Ribbon",
            "name": "inner_banner_ribbon",
            "type": "text",
            "instructions": "Red ribbon label below the heading.",
            "default_value": "Serving Our Community Together"
        },
        {
            "key": "field_psm_inner_banner_intro_ms",
            "label": "Intro",
            "name": "inner_banner_intro",
            "type": "textarea",
            "instructions": "Description paragraph in the banner.",
            "default_value": "Working together to support our local community and ensure Port St Mary remains a vibrant, welcoming and safe place for all.",
            "rows": 3
        },
        {
            "key": "field_psm_inner_banner_image_ms",
            "label": "Background Image",
            "name": "inner_banner_image",
            "type": "image",
            "instructions": "Banner background image.",
            "return_format": "url",
            "preview_size": "medium",
            "mime_types": "jpg,jpeg,png,webp"
        },
        {
            "key": "field_psm_ms_tab_commitment",
            "label": "Our Commitment",
            "name": "",
            "type": "tab",
            "placement": "top",
            "endpoint": 0,
            "selected": 0
        },
        {
            "key": "field_psm_mission_statement_image",
            "label": "Image",
            "name": "mission_statement_image",
            "type": "image",
            "instructions": "Single image for the left column.",
            "return_format": "url",
            "preview_size": "medium",
            "mime_types": "jpg,jpeg,png,webp",
            "wrapper": { "width": "50" }
        },
        {
            "key": "field_psm_mission_statement_badge",
            "label": "Eyebrow",
            "name": "mission_statement_badge",
            "type": "text",
            "default_value": "Port St Mary Mission Statement",
            "wrapper": { "width": "50" }
        },
        {
            "key": "field_psm_mission_statement_title",
            "label": "Heading",
            "name": "mission_statement_title",
            "type": "text",
            "default_value": "Our Commitment to the Community",
            "wrapper": { "width": "50" }
        },
        {
            "key": "field_psm_mission_statement_body",
            "label": "Body Text",
            "name": "mission_statement_body",
            "type": "textarea",
            "instructions": "One paragraph per line. The first line displays with the red accent.",
            "rows": 6,
            "default_value": "The Port St Mary Commissioners are committed to serving our community with transparency, integrity and care. Our mission is to support local needs, maintain essential services and help Port St Mary thrive as a vibrant seaside village.\r\nWe work collaboratively with residents, local organisations and stakeholders to deliver services that reflect the values and priorities of our community. Through open communication and responsible stewardship, we aim to build trust and strengthen community engagement.\r\nOur focus is on maintaining public spaces, supporting local initiatives and ensuring that decisions are made in the best interests of those who live, work and visit Port St Mary. We are dedicated to listening, responding and acting with accountability at all times.",
            "conditional_logic": [
                [
                    {
                        "field": "field_psm_mission_statement_title",
                        "operator": "!=empty"
                    }
                ]
            ]
        },
        {
            "key": "field_psm_mission_statement_document_label",
            "label": "Document Label",
            "name": "mission_statement_document_label",
            "type": "text",
            "instructions": "Link text for the mission statement PDF.",
            "default_value": "BM Mission Statement July 2024",
            "wrapper": { "width": "50" },
            "conditional_logic": [
                [
                    {
                        "field": "field_psm_mission_statement_title",
                        "operator": "!=empty"
                    }
                ]
            ]
        },
        {
            "key": "field_psm_mission_statement_document_file",
            "label": "Document PDF",
            "name": "mission_statement_document_file",
            "type": "file",
            "instructions": "PDF download for the document link.",
            "return_format": "url",
            "mime_types": "pdf",
            "wrapper": { "width": "50" },
            "conditional_logic": [
                [
                    {
                        "field": "field_psm_mission_statement_document_label",
                        "operator": "!=empty"
                    }
                ]
            ]
        }
    ],
    "location": [
        [
            {
                "param": "page_template",
                "operator": "==",
                "value": "page-mission-statement.php"
            }
        ]
    ],
    "menu_order": 30,
    "position": "normal",
    "style": "default",
    "label_placement": "top",
    "instruction_placement": "label",
    "hide_on_screen": "",
    "active": true,
    "description": "Inner banner and commitment section for the Board Mission Statement page.",
    "show_in_rest": 0,
    "modified": 1780500200
}
