{
    "key": "group_psm_page_inner_banner",
    "title": "Page — Inner Banner (deprecated)",
    "fields": [],
    "location": [],
    "menu_order": 5,
    "position": "normal",
    "style": "default",
    "label_placement": "top",
    "instruction_placement": "label",
    "hide_on_screen": "",
    "active": false,
    "description": "Deprecated. Inner banner fields live on each page template field group. Sync to remove duplicate fields on Where to Eat.",
    "show_in_rest": 0,
    "modified": 1750035600
}
